setup.py
xunlei.py
xunlei_cli
xunlei.egg-info/PKG-INFO
xunlei.egg-info/SOURCES.txt
xunlei.egg-info/dependency_links.txt
xunlei.egg-info/requires.txt
xunlei.egg-info/top_level.txt