Metadata-Version: 1.0
Name: xunlei
Version: 0.1.2
Summary: Basic API for Xunlei Lixian
Home-page: http://github.com/adieu/xunlei
Author: Ivan Diao
Author-email: adieu@adieu.me
License: BSD
Platform: UNKNOWN
Classifier: Development Status :: 4 - Beta
Classifier: Environment :: Console
Classifier: Intended Audience :: End Users/Desktop
Classifier: Intended Audience :: Developers
Classifier: Operating System :: OS Independent
Classifier: Topic :: Utilities
Classifier: Topic :: Communications :: File Sharing
